aria/__init__.py
aria/cli.py
aria/config.py
aria/logger.py
aria/output.py
aria/core/__init__.py
aria/core/policy.py
aria/core/templates.py
aria/core/validator.py
aria/templates/collaborative.yml
aria/templates/default.yml
aria/templates/docs_only.yml
aria/templates/strict.yml
aria/tools/policy_to_iderules.py
aria_framework-0.1.1a0.dist-info/METADATA
aria_framework-0.1.1a0.dist-info/WHEEL
aria_framework-0.1.1a0.dist-info/entry_points.txt
aria_framework-0.1.1a0.dist-info/licenses/LICENSE
aria_framework-0.1.1a0.dist-info/RECORD
